monstermash/__init__.py
monstermash/__main__.py
monstermash/config.py
monstermash/crypt.py
monstermash/datamodels.py
monstermash/parser.py
monstermash/utils/__init__.py
monstermash/utils/file.py
monstermash-1.13.0.dist-info/METADATA
monstermash-1.13.0.dist-info/WHEEL
monstermash-1.13.0.dist-info/RECORD
