Metadata-Version: 2.3
Name: monstermash
Version: 1.13.0
Summary: 
Author: Mitchell Lisle
Author-email: m.lisle90@gmail.com
Requires-Python: >3.9.1,<4.0
Classifier: Programming Language :: Python :: 3
Classifier: Programming Language :: Python :: 3.10
Classifier: Programming Language :: Python :: 3.11
Classifier: Programming Language :: Python :: 3.12
Classifier: Programming Language :: Python :: 3.13
Requires-Dist: click (>=8.1.3,<9.0.0)
Requires-Dist: cryptography (>=44.0.0)
Requires-Dist: pydantic (>=2.0,<3.0)
Requires-Dist: pydantic-settings (>=2.0.0,<3.0.0)
Requires-Dist: pynacl (>=1.5.0,<2.0.0)
